hsi_preprocessing_toolkit/__init__.py
hsi_preprocessing_toolkit/__main__.py
hsi_preprocessing_toolkit/algorithm.py
hsi_preprocessing_toolkit/asset/icon.ico
hsi_preprocessing_toolkit/asset/page/about.en.md
hsi_preprocessing_toolkit/asset/page/about.zh.md
hsi_preprocessing_toolkit/asset/page/calc_formula.png
hsi_preprocessing_toolkit/common.py
hsi_preprocessing_toolkit/component/create_logger.py
hsi_preprocessing_toolkit/page/about.py
hsi_preprocessing_toolkit/page/hsi_preprocessing.py
hsi_preprocessing_toolkit/page/scanner_calc.py
hsi_preprocessing_toolkit/util.py
hsi_preprocessing_toolkit-2.2.2.dist-info/WHEEL
hsi_preprocessing_toolkit-2.2.2.dist-info/entry_points.txt
hsi_preprocessing_toolkit-2.2.2.dist-info/METADATA
hsi_preprocessing_toolkit-2.2.2.dist-info/RECORD
