Metadata-Version: 2.4
Name: hsi-preprocessing-toolkit
Version: 2.2.2
Summary: HSI Preprocessing Toolkit
Author: songyz2023
Author-email: songyz2023 <songyz2023dlut@outlook.com>
License-Expression: AGPL-3.0-only
Classifier: Programming Language :: Python
Classifier: Programming Language :: Python :: 3.13
Classifier: Programming Language :: Python :: Implementation :: CPython
Requires-Dist: einops>=0.8.0
Requires-Dist: gradio>=5.50.0,<6.0.0
Requires-Dist: matplotlib>=3.10.0
Requires-Dist: opencv-python>=4.13.0.90
Requires-Dist: rasterio>=1.4.0
Requires-Dist: rs-fusion-datasets>=0.16.0
Requires-Dist: scipy>=1.16.0
Requires-Dist: webui2>=2.5.6
Requires-Python: >=3.13
Project-URL: Documentation, https://github.com/songyz2019/hsi-preprocessing-toolkit#readme
Project-URL: Issues, https://github.com/songyz2019/hsi-preprocessing-toolkit/issues
Project-URL: Source, https://github.com/songyz2019/hsi-preprocessing-toolkit
